README.rst
setup.py
argy/__init__.py
argy/argy.py
argy.egg-info/PKG-INFO
argy.egg-info/SOURCES.txt
argy.egg-info/dependency_links.txt
argy.egg-info/top_level.txt