Metadata-Version: 1.0
Name: argy
Version: 0.0.2
Summary: Simple tool for creating CLI applications
Home-page: https://github.com/cheif/argy
Author: Dan Berglund
Author-email: dan@berglund.io
License: UNKNOWN
Platform: UNKNOWN
